[
  {
    "title": "Best Coffee Brands in Italy",
    "slug": "best-coffee-brands-italy",
    "date": "2026-05-02",
    "excerpt": "Italian coffee brands remain dominant in global espresso culture.",
    "content": "<p>Italy remains one of the most influential countries in global coffee culture.</p><p>Brands like Lavazza and Illy helped define espresso worldwide.</p>"
  },
  {
    "title": "Why Japanese Coffee Culture Is Exploding",
    "slug": "japanese-coffee-culture",
    "date": "2026-05-02",
    "excerpt": "Japan has become one of the most advanced specialty coffee markets.",
    "content": "<p>Japanese coffee culture blends precision, aesthetics, and specialty roasting.</p>"
  }
]